screenman/__init__.py
screenman/cli.py
screenman/config.py
screenman/edid.py
screenman/screen.py
screenman/utils.py
screenman-0.1.1.dist-info/LICENSE
screenman-0.1.1.dist-info/METADATA
screenman-0.1.1.dist-info/WHEEL
screenman-0.1.1.dist-info/entry_points.txt
screenman-0.1.1.dist-info/top_level.txt
screenman-0.1.1.dist-info/RECORD
