Metadata-Version: 2.1
Name: screenman
Version: 0.1.1
Summary: A Python tool to manage and configure multi-monitor setups using EDID information, allowing users to apply predefined screen layouts with ease.
Author-email: Hendrik Klug <hendrik.klug@gmail.com>
License: MIT license
Project-URL: Homepage, https://github.com/Jimmy2027/screenman
Keywords: screenman
Classifier: License :: OSI Approved :: MIT License
Classifier: Natural Language :: English
Classifier: Programming Language :: Python :: 3
Classifier: Programming Language :: Python :: 3.6
Classifier: Programming Language :: Python :: 3.7
Classifier: Programming Language :: Python :: 3.8
Classifier: Programming Language :: Python :: 3.9
Classifier: Programming Language :: Python :: 3.10
Classifier: Programming Language :: Python :: 3.11
Classifier: Programming Language :: Python :: 3.12
Classifier: Programming Language :: Python :: 3.13
Requires-Python: >=3.9
License-File: LICENSE
Requires-Dist: Click >=7.0
Requires-Dist: loguru >=0.7.2
Requires-Dist: platformdirs >=4.3.6
Provides-Extra: test
Requires-Dist: pytest >=3 ; extra == 'test'
